pipecash/__init__.py
pipecash/agentWrapper.py
pipecash/cli.py
pipecash/debug.py
pipecash/logWrapper.py
pipecash/observedMethod.py
pipecash/optionTemplateSolver.py
pipecash/pipeObserver.py
pipecash/pipeScheduler.py
pipecash/runner.py
pipecash/scenario.py
pipecash/secretsManager.py
pipecash/validationUtils.py
pipecash/walletWrapper.py
pipecash-0.1.0.4.dist-info/AUTHORS.rst
pipecash-0.1.0.4.dist-info/LICENSE
pipecash-0.1.0.4.dist-info/METADATA
pipecash-0.1.0.4.dist-info/WHEEL
pipecash-0.1.0.4.dist-info/entry_points.txt
pipecash-0.1.0.4.dist-info/top_level.txt
pipecash-0.1.0.4.dist-info/RECORD
