Metadata-Version: 2.1
Name: pipecash
Version: 0.1.0.4
Summary: A framework for easy automation of Bitcoin related tasks. PipeCash is flexible due to it's plugin system and configuration options. Read more at http://pipe.cash/
Home-page: https://github.com/Pipe-Cash/pipecash
Author: Aleksandar Nikolaev Dinkov
Author-email: alexander.n.dinkov@gmail.com
License: OPEN BLOCKCHAIN-SPECIFIC LICENSE
Keywords: pipecash
Platform: UNKNOWN
Classifier: Development Status :: 2 - Pre-Alpha
Classifier: Intended Audience :: Developers
Classifier: Natural Language :: English
Classifier: Programming Language :: Python :: 3
Classifier: Programming Language :: Python :: 3.4
Classifier: Programming Language :: Python :: 3.5
Classifier: Programming Language :: Python :: 3.6
Classifier: Programming Language :: Python :: 3.7
Requires-Dist: Click (>=6.0)
Requires-Dist: schedule (==0.5.0)
